{
  "field": "single_power_class",
  "m": {
    "field": "lamp_bead_type",
    "RGBW": {
      "field": "lamp_bead_model",
      "CREE 四合一": ["3000", "4000", "6500"]
    },
    "W": {
      "field": "lamp_bead_model",
      "OSRAM 3030": [
        "2200",
        "2700",
        "3000",
        "3500",
        "4000",
        "4500",
        "5000",
        "5700",
        "6500"
      ],
      "天电 3030": ["1800", "2200", "6500"]
    }
  },
  "s": {
    "field": "lamp_bead_type",
    "RGBW": {
      "field": "lamp_bead_model",
      "国产5050四合一": ["3000", "4000", "5600"]
    },
    "W": {
      "field": "model_number",
      "CV3E": {
        "field": "lamp_bead_model",
        "OSRAM 3014": ["2700", "3000", "3500", "4000", "5000", "5700", "6500"]
      },
      "others": {
        "field": "lamp_bead_model",
        "OSRAM 2835": [
          "2200",
          "2700",
          "3000",
          "3500",
          "4000",
          "4500",
          "5000",
          "5700",
          "6500"
        ],
        "天电 3014": ["1800", "2700", "6500"]
      }
    }
  }
}
